Compiled from "GeekGame.java"
public class GeekGame extends java.awt.Frame implements java.awt.event.ActionListener {
  java.awt.TextField textField1;

  java.awt.Button button1;

  java.awt.Button button2;

  javax.script.Invocable invocable;

  GeekGame();
    Code:
       0: aload_0
       1: invokespecial #1                  // Method java/awt/Frame."<init>":()V
       4: aload_0
       5: sipush        300
       8: sipush        300
      11: invokevirtual #2                  // Method setSize:(II)V
      14: aload_0
      15: iconst_1
      16: invokevirtual #3                  // Method setVisible:(Z)V
      19: aload_0
      20: new           #4                  // class javax/swing/BoxLayout
      23: dup
      24: aload_0
      25: iconst_1
      26: invokespecial #5                  // Method javax/swing/BoxLayout."<init>":(Ljava/awt/Container;I)V
      29: invokevirtual #6                  // Method setLayout:(Ljava/awt/LayoutManager;)V
      32: new           #7                  // class java/awt/Label
      35: dup
      36: ldc           #8                  // String Flag:
      38: invokespecial #9                  // Method java/awt/Label."<init>":(Ljava/lang/String;)V
      41: astore_1
      42: aload_0
      43: new           #10                 // class java/awt/TextField
      46: dup
      47: ldc           #11                 // String flag{...}
      49: invokespecial #12                 // Method java/awt/TextField."<init>":(Ljava/lang/String;)V
      52: putfield      #13                 // Field textField1:Ljava/awt/TextField;
      55: aload_0
      56: new           #14                 // class java/awt/Button
      59: dup
      60: ldc           #15                 // String Check Flag 1
      62: invokespecial #16                 // Method java/awt/Button."<init>":(Ljava/lang/String;)V
      65: putfield      #17                 // Field button1:Ljava/awt/Button;
      68: aload_0
      69: getfield      #17                 // Field button1:Ljava/awt/Button;
      72: aload_0
      73: invokevirtual #18                 // Method java/awt/Button.addActionListener:(Ljava/awt/event/ActionListener;)V
      76: aload_0
      77: new           #14                 // class java/awt/Button
      80: dup
      81: ldc           #19                 // String Check Flag 2
      83: invokespecial #16                 // Method java/awt/Button."<init>":(Ljava/lang/String;)V
      86: putfield      #20                 // Field button2:Ljava/awt/Button;
      89: aload_0
      90: getfield      #20                 // Field button2:Ljava/awt/Button;
      93: aload_0
      94: invokevirtual #18                 // Method java/awt/Button.addActionListener:(Ljava/awt/event/ActionListener;)V
      97: aload_0
      98: aload_1
      99: invokevirtual #21                 // Method add:(Ljava/awt/Component;)Ljava/awt/Component;
     102: pop
     103: aload_0
     104: aload_0
     105: getfield      #13                 // Field textField1:Ljava/awt/TextField;
     108: invokevirtual #21                 // Method add:(Ljava/awt/Component;)Ljava/awt/Component;
     111: pop
     112: aload_0
     113: aload_0
     114: getfield      #17                 // Field button1:Ljava/awt/Button;
     117: invokevirtual #21                 // Method add:(Ljava/awt/Component;)Ljava/awt/Component;
     120: pop
     121: aload_0
     122: aload_0
     123: getfield      #20                 // Field button2:Ljava/awt/Button;
     126: invokevirtual #21                 // Method add:(Ljava/awt/Component;)Ljava/awt/Component;
     129: pop
     130: new           #22                 // class javax/script/ScriptEngineManager
     133: dup
     134: invokespecial #23                 // Method javax/script/ScriptEngineManager."<init>":()V
     137: astore_2
     138: aload_2
     139: ldc           #24                 // String nashorn
     141: invokevirtual #25                 // Method javax/script/ScriptEngineManager.getEngineByName:(Ljava/lang/String;)Ljavax/script/ScriptEngine;
     144: astore_3
     145: ldc           #26                 // String \u0089\u009a\u0081\u008c\u009b\u0086\u0080\u0081Ï\u008c\u0087\u008a\u008c\u0084\u0089\u0083\u008e\u0088ÝÇ°ß\u0097\u008e×Ü\u008a\u0097ÝÆ\u0094\u0099\u008e\u009dÏ°ß\u0097ØÝÛ\u008dÒ´È\u008c\u0087\u008e\u009d¬\u0080\u008b\u008a®\u009bÈÃÈ\u0082\u008e\u009fÈÃÈÈÃÈ\u009c\u009f\u0083\u0086\u009bÈÃÈ\u009c\u009b\u009d\u0086\u0081\u0088\u0086\u0089\u0096ÈÃÈ¬\u0080\u009d\u009d\u008a\u008c\u009bÈÃÈ¸\u009d\u0080\u0081\u0088ÈÃÈ\u0085ÂÈ²Ô\u009d\u008a\u009b\u009a\u009d\u0081ÏÇ¥¼ ¡´°ß\u0097ØÝÛ\u008d´Û²²Ç°ß\u0097\u008e×Ü\u008a\u0097Ý´°ß\u0097ØÝÛ\u008d´Ü²²Ç°ß\u0097ØÝÛ\u008d´Ý²Æ´°ß\u0097ØÝÛ\u008d´Þ²²Ç\u0089\u009a\u0081\u008c\u009b\u0086\u0080\u0081Ç°ß\u0097\u008e×Ü\u008a\u0097ÜÆ\u0094\u009d\u008a\u009b\u009a\u009d\u0081Ï°ß\u0097\u008e×Ü\u008a\u0097Ü´°ß\u0097ØÝÛ\u008d´ß²²ÇßÆ\u0092ÆÆÒÒÏ¥¼ ¡´°ß\u0097ØÝÛ\u008d´Û²²Ç´ßÃÞÚÃÞÙÃÞØÃÜßÃÞßÚÃÞÙÃÜÞÃÞÙÃÙØÃÜÃÜÜÃÚÃÙßÃÛÃÞßÙÃÙÃÛÞÃßÃÞÃÙØÃÜÃÞÙÃÛÃÙÃÜÜÃÝÜÝ²´°ß\u0097ØÝÛ\u008d´Þ²²Ç\u0089\u009a\u0081\u008c\u009b\u0086\u0080\u0081Ç°ß\u0097\u008e×Ü\u008a\u0097ÜÆ\u0094\u009d\u008a\u009b\u009a\u009d\u0081ÏÇ\u008c\u0087\u008a\u008c\u0084\u0089\u0083\u008e\u0088ÝÄÏ°ß\u0097ØÝÛ\u008d´Ý²Æ´°ß\u0097ØÝÛ\u008d´ß²²Ç°ß\u0097\u008e×Ü\u008a\u0097ÜÆ\u0092ÆÆÐ°ß\u0097ØÝÛ\u008d´Ú²Õ°ß\u0097ØÝÛ\u008d´Ù²Æ\u0092
     147: astore        4
     149: new           #27                 // class java/lang/StringBuilder
     152: dup
     153: invokespecial #28                 // Method java/lang/StringBuilder."<init>":()V
     156: astore        5
     158: iconst_0
     159: istore        6
     161: iload         6
     163: aload         4
     165: invokevirtual #29                 // Method java/lang/String.length:()I
     168: if_icmpge     195
     171: aload         5
     173: aload         4
     175: iload         6
     177: invokevirtual #30                 // Method java/lang/String.charAt:(I)C
     180: sipush        239
     183: ixor
     184: i2c
     185: invokevirtual #31                 // Method java/lang/StringBuilder.append:(C)Ljava/lang/StringBuilder;
     188: pop
     189: iinc          6, 1
     192: goto          161
     195: aload_3
     196: aload         5
     198: invokevirtual #32                 // Method java/lang/StringBuilder.toString:()Ljava/lang/String;
     201: invokeinterface #33,  2           // InterfaceMethod javax/script/ScriptEngine.eval:(Ljava/lang/String;)Ljava/lang/Object;
     206: pop
     207: goto          248
     210: astore        4
     212: new           #35                 // class java/io/StringWriter
     215: dup
     216: invokespecial #36                 // Method java/io/StringWriter."<init>":()V
     219: astore        5
     221: new           #37                 // class java/io/PrintWriter
     224: dup
     225: aload         5
     227: invokespecial #38                 // Method java/io/PrintWriter."<init>":(Ljava/io/Writer;)V
     230: astore        6
     232: aload         4
     234: aload         6
     236: invokevirtual #39                 // Method java/lang/Exception.printStackTrace:(Ljava/io/PrintWriter;)V
     239: aconst_null
     240: aload         5
     242: invokevirtual #40                 // Method java/io/StringWriter.toString:()Ljava/lang/String;
     245: invokestatic  #41                 // Method javax/swing/JOptionPane.showMessageDialog:(Ljava/awt/Component;Ljava/lang/Object;)V
     248: aload_0
     249: aload_3
     250: checkcast     #42                 // class javax/script/Invocable
     253: putfield      #43                 // Field invocable:Ljavax/script/Invocable;
     256: aload_0
     257: new           #44                 // class GeekGame$1
     260: dup
     261: aload_0
     262: invokespecial #45                 // Method GeekGame$1."<init>":(LGeekGame;)V
     265: invokevirtual #46                 // Method addWindowListener:(Ljava/awt/event/WindowListener;)V
     268: return
    Exception table:
       from    to  target type
         145   207   210   Class java/lang/Exception

  public void actionPerformed(java.awt.event.ActionEvent);
    Code:
       0: aload_1
       1: invokevirtual #47                 // Method java/awt/event/ActionEvent.getSource:()Ljava/lang/Object;
       4: aload_0
       5: getfield      #17                 // Field button1:Ljava/awt/Button;
       8: if_acmpne     62
      11: aload_0
      12: getfield      #13                 // Field textField1:Ljava/awt/TextField;
      15: invokevirtual #48                 // Method java/awt/TextField.getText:()Ljava/lang/String;
      18: ldc           #49                 // String UTF-8
      20: invokevirtual #50                 // Method java/lang/String.getBytes:(Ljava/lang/String;)[B
      23: astore_2
      24: invokestatic  #51                 // Method java/util/Base64.getEncoder:()Ljava/util/Base64$Encoder;
      27: aload_2
      28: invokevirtual #52                 // Method java/util/Base64$Encoder.encodeToString:([B)Ljava/lang/String;
      31: invokestatic  #53                 // Method rot13:(Ljava/lang/String;)Ljava/lang/String;
      34: astore_3
      35: ldc           #54                 // String MzkuM8gmZJ6jZJHgnaMuqy4lMKM4
      37: aload_3
      38: invokevirtual #55                 // Method java/lang/String.equals:(Ljava/lang/Object;)Z
      41: ifeq          53
      44: aconst_null
      45: ldc           #56                 // String Correct
      47: invokestatic  #41                 // Method javax/swing/JOptionPane.showMessageDialog:(Ljava/awt/Component;Ljava/lang/Object;)V
      50: goto          59
      53: aconst_null
      54: ldc           #57                 // String Wrong
      56: invokestatic  #41                 // Method javax/swing/JOptionPane.showMessageDialog:(Ljava/awt/Component;Ljava/lang/Object;)V
      59: goto          112
      62: aload_0
      63: getfield      #43                 // Field invocable:Ljavax/script/Invocable;
      66: aload_1
      67: invokevirtual #47                 // Method java/awt/event/ActionEvent.getSource:()Ljava/lang/Object;
      70: aload_0
      71: getfield      #20                 // Field button2:Ljava/awt/Button;
      74: if_acmpne     82
      77: ldc           #58                 // String checkflag2
      79: goto          84
      82: ldc           #59                 // String checkflag3
      84: iconst_1
      85: anewarray     #60                 // class java/lang/Object
      88: dup
      89: iconst_0
      90: aload_0
      91: getfield      #13                 // Field textField1:Ljava/awt/TextField;
      94: invokevirtual #48                 // Method java/awt/TextField.getText:()Ljava/lang/String;
      97: aastore
      98: invokeinterface #61,  3           // InterfaceMethod javax/script/Invocable.invokeFunction:(Ljava/lang/String;[Ljava/lang/Object;)Ljava/lang/Object;
     103: astore_2
     104: aconst_null
     105: aload_2
     106: checkcast     #62                 // class java/lang/String
     109: invokestatic  #41                 // Method javax/swing/JOptionPane.showMessageDialog:(Ljava/awt/Component;Ljava/lang/Object;)V
     112: goto          148
     115: astore_2
     116: new           #35                 // class java/io/StringWriter
     119: dup
     120: invokespecial #36                 // Method java/io/StringWriter."<init>":()V
     123: astore_3
     124: new           #37                 // class java/io/PrintWriter
     127: dup
     128: aload_3
     129: invokespecial #38                 // Method java/io/PrintWriter."<init>":(Ljava/io/Writer;)V
     132: astore        4
     134: aload_2
     135: aload         4
     137: invokevirtual #39                 // Method java/lang/Exception.printStackTrace:(Ljava/io/PrintWriter;)V
     140: aconst_null
     141: aload_3
     142: invokevirtual #40                 // Method java/io/StringWriter.toString:()Ljava/lang/String;
     145: invokestatic  #41                 // Method javax/swing/JOptionPane.showMessageDialog:(Ljava/awt/Component;Ljava/lang/Object;)V
     148: return
    Exception table:
       from    to  target type
           0   112   115   Class java/lang/Exception

  static java.lang.String rot13(java.lang.String);
    Code:
       0: new           #27                 // class java/lang/StringBuilder
       3: dup
       4: invokespecial #28                 // Method java/lang/StringBuilder."<init>":()V
       7: astore_1
       8: iconst_0
       9: istore_2
      10: iload_2
      11: aload_0
      12: invokevirtual #29                 // Method java/lang/String.length:()I
      15: if_icmpge     157
      18: aload_0
      19: iload_2
      20: invokevirtual #30                 // Method java/lang/String.charAt:(I)C
      23: istore_3
      24: iload_3
      25: bipush        97
      27: if_icmplt     45
      30: iload_3
      31: bipush        109
      33: if_icmpgt     45
      36: iload_3
      37: bipush        13
      39: iadd
      40: i2c
      41: istore_3
      42: goto          145
      45: iload_3
      46: bipush        65
      48: if_icmplt     66
      51: iload_3
      52: bipush        77
      54: if_icmpgt     66
      57: iload_3
      58: bipush        13
      60: iadd
      61: i2c
      62: istore_3
      63: goto          145
      66: iload_3
      67: bipush        110
      69: if_icmplt     87
      72: iload_3
      73: bipush        122
      75: if_icmpgt     87
      78: iload_3
      79: bipush        13
      81: isub
      82: i2c
      83: istore_3
      84: goto          145
      87: iload_3
      88: bipush        78
      90: if_icmplt     108
      93: iload_3
      94: bipush        90
      96: if_icmpgt     108
      99: iload_3
     100: bipush        13
     102: isub
     103: i2c
     104: istore_3
     105: goto          145
     108: iload_3
     109: bipush        53
     111: if_icmplt     128
     114: iload_3
     115: bipush        57
     117: if_icmpgt     128
     120: iload_3
     121: iconst_5
     122: isub
     123: i2c
     124: istore_3
     125: goto          145
     128: iload_3
     129: bipush        48
     131: if_icmplt     145
     134: iload_3
     135: bipush        52
     137: if_icmpgt     145
     140: iload_3
     141: iconst_5
     142: iadd
     143: i2c
     144: istore_3
     145: aload_1
     146: iload_3
     147: invokevirtual #31                 // Method java/lang/StringBuilder.append:(C)Ljava/lang/StringBuilder;
     150: pop
     151: iinc          2, 1
     154: goto          10
     157: aload_1
     158: invokevirtual #32                 // Method java/lang/StringBuilder.toString:()Ljava/lang/String;
     161: areturn

  public static void main(java.lang.String[]);
    Code:
       0: new           #63                 // class GeekGame
       3: dup
       4: invokespecial #64                 // Method "<init>":()V
       7: astore_1
       8: return
}
